ca_cdk8s_constructs/__init__.py
ca_cdk8s_constructs/blackbox_probe.py
ca_cdk8s_constructs/cdk8s_helm_chart.py
ca_cdk8s_constructs/container_resources.py
ca_cdk8s_constructs/helpers.py
ca_cdk8s_constructs/hpa.py
ca_cdk8s_constructs/imports/com/coreos/monitoring/__init__.py
ca_cdk8s_constructs/imports/com/coreos/monitoring/_jsii/__init__.py
ca_cdk8s_constructs/imports/com/coreos/monitoring/_jsii/comcoreosmonitoring@0.0.0.jsii.tgz
ca_cdk8s_constructs/imports/com/coreos/monitoring/py.typed
ca_cdk8s_constructs/imports/io/external_secrets/__init__.py
ca_cdk8s_constructs/imports/io/external_secrets/_jsii/__init__.py
ca_cdk8s_constructs/imports/io/external_secrets/_jsii/ioexternal-secrets@0.0.0.jsii.tgz
ca_cdk8s_constructs/imports/io/external_secrets/generators/__init__.py
ca_cdk8s_constructs/imports/io/external_secrets/generators/_jsii/__init__.py
ca_cdk8s_constructs/imports/io/external_secrets/generators/_jsii/ioexternal-secretsgenerators@0.0.0.jsii.tgz
ca_cdk8s_constructs/imports/io/external_secrets/generators/py.typed
ca_cdk8s_constructs/imports/io/external_secrets/py.typed
ca_cdk8s_constructs/imports/io/k8s/autoscaling/__init__.py
ca_cdk8s_constructs/imports/io/k8s/autoscaling/_jsii/__init__.py
ca_cdk8s_constructs/imports/io/k8s/autoscaling/_jsii/iok8sautoscaling@0.0.0.jsii.tgz
ca_cdk8s_constructs/imports/io/k8s/autoscaling/py.typed
ca_cdk8s_constructs/pod_disruption_budget.py
ca_cdk8s_constructs/topology_spread.py
ca_cdk8s_constructs/vpa.py
ca_cdk8s_constructs-5.0.0.dist-info/WHEEL
ca_cdk8s_constructs-5.0.0.dist-info/METADATA
ca_cdk8s_constructs-5.0.0.dist-info/RECORD
