Metadata-Version: 2.3
Name: ca-cdk8s-constructs
Version: 5.0.0
Summary: A collection of cdk8s constructs
Author: Citizens Advice
Author-email: Citizens Advice <cloud.engineering@citizensadvice.org.uk>
License:                                  Apache License
Requires-Dist: cdk8s>=2.70.11
Requires-Dist: cdk8s-plus-32>=2.4.1
Requires-Dist: pyyaml>=6.0.2
Requires-Dist: aws-cdk-lib>=2.214.0
Requires-Python: >=3.10
Project-URL: Homepage, https://github.com/citizensadvice/ca-cdk8s-constructs
Project-URL: Repository, https://github.com/matthewcane/ca-cdk8s-constructs
Project-URL: Issues, https://github.com/citizensadvice/ca-cdk8s-constructs/issues
Project-URL: Changelog, https://github.com/citizensadvice/ca-cdk8s-constructs/releases
